uliweb_apps/__init__.py
uliweb_apps/async_download/__init__.py
uliweb_apps/async_download/conf.py
uliweb_apps/async_download/info.ini
uliweb_apps/async_download/settings.ini
uliweb_apps/async_download/views.py
uliweb_apps/async_download/static/readme.txt
uliweb_apps/async_download/templates/inc_table_async.html
uliweb_apps/async_download/templates/readme.txt
uliweb_apps/async_tasks/__init__.py
uliweb_apps/async_tasks/conf.py
uliweb_apps/async_tasks/daemon.py
uliweb_apps/async_tasks/info.ini
uliweb_apps/async_tasks/models.py
uliweb_apps/async_tasks/settings.ini
uliweb_apps/async_tasks/tasks.py
uliweb_apps/async_tasks/views.py
uliweb_apps/async_tasks/workers.py
uliweb_apps/async_tasks/static/readme.txt
uliweb_apps/async_tasks/templates/readme.txt
uliweb_apps/async_tasks/templates/AsyncTasksView/edit.html
uliweb_apps/async_tasks/templates/AsyncTasksView/list.html
uliweb_apps/async_tasks/templates/AsyncTasksView/view.html
uliweb_apps/async_tasks/test/send.py
uliweb_apps/async_tasks/test/test_async.py
uliweb_apps/cron/__init__.py
uliweb_apps/cron/commands.py
uliweb_apps/cron/conf.py
uliweb_apps/cron/config.ini
uliweb_apps/cron/daemon.py
uliweb_apps/cron/forms.py
uliweb_apps/cron/info.ini
uliweb_apps/cron/models.py
uliweb_apps/cron/requirements.txt
uliweb_apps/cron/settings.ini
uliweb_apps/cron/views.py
uliweb_apps/cron/static/readme.txt
uliweb_apps/cron/static/cron/show_workflow.js
uliweb_apps/cron/taglibs/cron/workflow.html
uliweb_apps/cron/templates/cron_layout.html
uliweb_apps/cron/templates/readme.txt
uliweb_apps/cron/templates/CronView/add.html
uliweb_apps/cron/templates/CronView/add_task.html
uliweb_apps/cron/templates/CronView/edit.html
uliweb_apps/cron/templates/CronView/list.html
uliweb_apps/cron/templates/CronView/view.html
uliweb_apps/cron/templates/CronView/view_workflow.html
uliweb_apps/cron/templates/CronView/workflow.html
uliweb_apps/cron/test/test_cron.py
uliweb_apps/login/README.md
uliweb_apps/login/__init__.py
uliweb_apps/login/settings.ini
uliweb_apps-0.1.0.dist-info/METADATA
uliweb_apps-0.1.0.dist-info/WHEEL
uliweb_apps-0.1.0.dist-info/top_level.txt
uliweb_apps-0.1.0.dist-info/RECORD
