Metadata-Version: 2.1
Name: uliweb-apps
Version: 0.1.0
Summary: uliweb-apps
Home-page: https://github.com/limodou/uliweb-apps
Author: limodou
Author-email: limodou@gmail.com
License: BSD
Platform: any
Classifier: Development Status :: 4 - Beta
Classifier: Environment :: Web Environment
Classifier: Intended Audience :: Developers
Classifier: License :: OSI Approved :: BSD License
Classifier: Operating System :: OS Independent
Classifier: Programming Language :: Python
Classifier: Topic :: Software Development :: Libraries :: Python Modules
Requires-Dist: uliweb3
Requires-Dist: uliweb-ui
Requires-Dist: uliweb-layout
